{
  "wave": 4,
  "started_at": "2026-04-26T02:00:00Z",
  "shipped": [
    {
      "wave": 1,
      "workers": ["A,B,C,D,E,F — initial 7 surfaces + data + libs"],
      "result": "10 surfaces, prod build clean, pushed."
    },
    {
      "wave": 2,
      "workers": [
        "1: vitest suite (65 tests)",
        "2: /experiments",
        "3: /playbooks (worker hit org limit; finished manually)",
        "4: /day1 interactive timeline",
        "5: strategy deepening + week-1 metrics strip (partial; finished manually)",
        "6: Loom script + README + mobile audit"
      ],
      "result": "/experiments, /playbooks, /day1 added. Strategy memo deepened. Loom + README + audit on disk."
    },
    {
      "wave": 3,
      "workers": [
        "3.1: per-route SEO metadata + OpenGraph + nav add /day1",
        "3.2: hamburger MobileNav + sticky lead CTA bar",
        "3.3: copy scrub — 18 user-facing em-dashes removed; strategic phrases preserved"
      ],
      "result": "All 10 surfaces have metadata. Mobile nav works. User-facing copy is em-dash-clean. Pushed."
    }
  ],
  "in_flight": [],
  "next_wave_4_candidates": [
    "Add /sources citation page with all data + claim attribution",
    "Build a tiny Slack-thread mockup component for /day1 showing the day-end brief artifact",
    "Add /pricing-experiment page showing the live A/B test variant runner with CTR mock",
    "Add a /channel-mix page with bottoms-up channel ROI by stage",
    "Add a /reference-customers component to /enterprise (3 mocked references with quotes)",
    "Add OpenGraph image generation (next/og) for social card previews",
    "Tighten /pipeline empty-state and density on cards",
    "Add keyboard-shortcuts overlay (press ? to open)",
    "Add a /metrics admin page with WEEK_1 + WEEK_4 strips side-by-side"
  ]
}
